{
	"info": {
		"_postman_id": "f98409c3-9059-4b05-a962-0953cd9b9d54",
		"name": "API TEST - PRN232_SU25_SE170076.api",
		"schema": "https://schema.getpostman.com/json/collection/v2.1.0/collection.json",
		"_exporter_id": "36975475"
	},
	"item": [
		{
			"name": "Login success",
			"request": {
				"method": "POST",
				"header": [],
				"body": {
					"mode": "raw",
					"raw": "{\r\n  \"email\": \"admin@leopard.com\",\r\n  \"password\": \"@1\"\r\n}",
					"options": {
						"raw": {
							"language": "json"
						}
					}
				},
				"url": {
					"raw": "https://localhost:7096/api/auth",
					"protocol": "https",
					"host": [
						"localhost"
					],
					"port": "7096",
					"path": [
						"api",
						"auth"
					]
				}
			},
			"response": []
		},
		{
			"name": "Login failed",
			"request": {
				"method": "POST",
				"header": [],
				"body": {
					"mode": "raw",
					"raw": "{\r\n  \"email\": \"admin@leopard.com\",\r\n  \"password\": \"@21\"\r\n}",
					"options": {
						"raw": {
							"language": "json"
						}
					}
				},
				"url": {
					"raw": "https://localhost:7096/api/auth",
					"protocol": "https",
					"host": [
						"localhost"
					],
					"port": "7096",
					"path": [
						"api",
						"auth"
					]
				}
			},
			"response": []
		},
		{
			"name": "Create",
			"request": {
				"auth": {
					"type": "bearer",
					"bearer": [
						{
							"key": "token",
							"value": "eyJhbGciOiJIUzI1NiIsInR5cCI6IkpXVCJ9.eyJzdWIiOiJhZG1pbiIsImp0aSI6ImRiMjFjZTcyLTc4OTMtNGJjYy1hMzY5LTEzNTZmNWExNWZkYiIsImV4cCI6MTc1MzA2Nzg0MywiaXNzIjoicGVwcm4yMzIiLCJhdWQiOiJwZXBybjIzMiJ9.KlysODuhqqFjBNAO2Kw81favVNDP58RcYQuDp4O7fb8",
							"type": "string"
						}
					]
				},
				"method": "POST",
				"header": [],
				"url": {
					"raw": "https://localhost:7096/api/LeopardProfile",
					"protocol": "https",
					"host": [
						"localhost"
					],
					"port": "7096",
					"path": [
						"api",
						"LeopardProfile"
					]
				}
			},
			"response": []
		},
		{
			"name": "Update",
			"request": {
				"auth": {
					"type": "bearer",
					"bearer": [
						{
							"key": "token",
							"value": "eyJhbGciOiJIUzI1NiIsInR5cCI6IkpXVCJ9.eyJzdWIiOiJhZG1pbiIsImp0aSI6ImRiMjFjZTcyLTc4OTMtNGJjYy1hMzY5LTEzNTZmNWExNWZkYiIsImV4cCI6MTc1MzA2Nzg0MywiaXNzIjoicGVwcm4yMzIiLCJhdWQiOiJwZXBybjIzMiJ9.KlysODuhqqFjBNAO2Kw81favVNDP58RcYQuDp4O7fb8",
							"type": "string"
						}
					]
				},
				"method": "PUT",
				"header": [],
				"url": {
					"raw": "https://localhost:7096/api/LeopardProfile/2",
					"protocol": "https",
					"host": [
						"localhost"
					],
					"port": "7096",
					"path": [
						"api",
						"LeopardProfile",
						"2"
					]
				}
			},
			"response": []
		},
		{
			"name": "Delete",
			"request": {
				"auth": {
					"type": "bearer",
					"bearer": [
						{
							"key": "token",
							"value": "eyJhbGciOiJIUzI1NiIsInR5cCI6IkpXVCJ9.eyJzdWIiOiJhZG1pbiIsImp0aSI6ImRiMjFjZTcyLTc4OTMtNGJjYy1hMzY5LTEzNTZmNWExNWZkYiIsImV4cCI6MTc1MzA2Nzg0MywiaXNzIjoicGVwcm4yMzIiLCJhdWQiOiJwZXBybjIzMiJ9.KlysODuhqqFjBNAO2Kw81favVNDP58RcYQuDp4O7fb8",
							"type": "string"
						}
					]
				},
				"method": "DELETE",
				"header": [],
				"url": {
					"raw": "https://localhost:7096/api/LeopardProfile/2",
					"protocol": "https",
					"host": [
						"localhost"
					],
					"port": "7096",
					"path": [
						"api",
						"LeopardProfile",
						"2"
					]
				}
			},
			"response": []
		},
		{
			"name": "Get list",
			"request": {
				"auth": {
					"type": "bearer",
					"bearer": [
						{
							"key": "token",
							"value": "eyJhbGciOiJIUzI1NiIsInR5cCI6IkpXVCJ9.eyJzdWIiOiJhZG1pbiIsImp0aSI6ImRiMjFjZTcyLTc4OTMtNGJjYy1hMzY5LTEzNTZmNWExNWZkYiIsImV4cCI6MTc1MzA2Nzg0MywiaXNzIjoicGVwcm4yMzIiLCJhdWQiOiJwZXBybjIzMiJ9.KlysODuhqqFjBNAO2Kw81favVNDP58RcYQuDp4O7fb8",
							"type": "string"
						}
					]
				},
				"method": "GET",
				"header": [],
				"url": {
					"raw": "https://localhost:7096/api/LeopardProfile",
					"protocol": "https",
					"host": [
						"localhost"
					],
					"port": "7096",
					"path": [
						"api",
						"LeopardProfile"
					]
				}
			},
			"response": []
		},
		{
			"name": "Get by ID",
			"request": {
				"auth": {
					"type": "bearer",
					"bearer": [
						{
							"key": "token",
							"value": "eyJhbGciOiJIUzI1NiIsInR5cCI6IkpXVCJ9.eyJzdWIiOiJhZG1pbiIsImp0aSI6ImRiMjFjZTcyLTc4OTMtNGJjYy1hMzY5LTEzNTZmNWExNWZkYiIsImV4cCI6MTc1MzA2Nzg0MywiaXNzIjoicGVwcm4yMzIiLCJhdWQiOiJwZXBybjIzMiJ9.KlysODuhqqFjBNAO2Kw81favVNDP58RcYQuDp4O7fb8",
							"type": "string"
						}
					]
				},
				"method": "GET",
				"header": [],
				"url": {
					"raw": "https://localhost:7096/api/LeopardProfile/1",
					"protocol": "https",
					"host": [
						"localhost"
					],
					"port": "7096",
					"path": [
						"api",
						"LeopardProfile",
						"1"
					]
				}
			},
			"response": []
		},
		{
			"name": "Search",
			"request": {
				"auth": {
					"type": "bearer",
					"bearer": [
						{
							"key": "token",
							"value": "eyJhbGciOiJIUzI1NiIsInR5cCI6IkpXVCJ9.eyJzdWIiOiJhZG1pbiIsImp0aSI6ImRiMjFjZTcyLTc4OTMtNGJjYy1hMzY5LTEzNTZmNWExNWZkYiIsImV4cCI6MTc1MzA2Nzg0MywiaXNzIjoicGVwcm4yMzIiLCJhdWQiOiJwZXBybjIzMiJ9.KlysODuhqqFjBNAO2Kw81favVNDP58RcYQuDp4O7fb8",
							"type": "string"
						}
					]
				},
				"method": "GET",
				"header": [],
				"url": {
					"raw": "https://localhost:7096/api/LeopardProfile/search?weight=35",
					"protocol": "https",
					"host": [
						"localhost"
					],
					"port": "7096",
					"path": [
						"api",
						"LeopardProfile",
						"search"
					],
					"query": [
						{
							"key": "weight",
							"value": "35"
						}
					]
				}
			},
			"response": []
		}
	]
}